accuralai_adaptive_tools/__init__.py
accuralai_adaptive_tools/contracts/__init__.py
accuralai_adaptive_tools/contracts/models.py
accuralai_adaptive_tools/contracts/protocols.py
accuralai_adaptive_tools/coordinator/__init__.py
accuralai_adaptive_tools/coordinator/v3.py
accuralai_adaptive_tools/registry/__init__.py
accuralai_adaptive_tools/registry/unified.py
accuralai_adaptive_tools/telemetry/__init__.py
accuralai_adaptive_tools/telemetry/collector.py
accuralai_adaptive_tools/telemetry/router.py
accuralai_adaptive_tools/telemetry/storage.py
accuralai_adaptive_tools/v1/__init__.py
accuralai_adaptive_tools/v1/system.py
accuralai_adaptive_tools/v1/approval/__init__.py
accuralai_adaptive_tools/v1/approval/workflow.py
accuralai_adaptive_tools/v1/sandbox/__init__.py
accuralai_adaptive_tools/v1/sandbox/executor.py
accuralai_adaptive_tools/v1/sandbox/safety_validator.py
accuralai_adaptive_tools/v1/synthesis/__init__.py
accuralai_adaptive_tools/v1/synthesis/code_generator.py
accuralai_adaptive_tools/v1/synthesis/llm_client.py
accuralai_adaptive_tools/v1/synthesis/templates.py
accuralai_adaptive_tools/v1/telemetry/__init__.py
accuralai_adaptive_tools/v1/telemetry/capability_detector.py
accuralai_adaptive_tools/v1/telemetry/failure_analyzer.py
accuralai_adaptive_tools/v1/telemetry/pattern_detector.py
accuralai_adaptive_tools/v1/telemetry/sequence_analyzer.py
accuralai_adaptive_tools/v2/__init__.py
accuralai_adaptive_tools/v2/system.py
accuralai_adaptive_tools/v2/execution/__init__.py
accuralai_adaptive_tools/v2/execution/context.py
accuralai_adaptive_tools/v2/execution/executor.py
accuralai_adaptive_tools/v2/execution/variable_resolver.py
accuralai_adaptive_tools/v2/optimization/__init__.py
accuralai_adaptive_tools/v2/optimization/ab_tester.py
accuralai_adaptive_tools/v2/optimization/bayesian.py
accuralai_adaptive_tools/v2/planlang/__init__.py
accuralai_adaptive_tools/v2/planlang/parser.py
accuralai_adaptive_tools/v2/planlang/schema.py
accuralai_adaptive_tools-0.2.1.dist-info/licenses/LICENSE
accuralai_adaptive_tools-0.2.1.dist-info/METADATA
accuralai_adaptive_tools-0.2.1.dist-info/WHEEL
accuralai_adaptive_tools-0.2.1.dist-info/entry_points.txt
accuralai_adaptive_tools-0.2.1.dist-info/top_level.txt
accuralai_adaptive_tools-0.2.1.dist-info/RECORD
